proto_compile/__init__.py
proto_compile/cli.py
proto_compile/options.py
proto_compile/plugins.py
proto_compile/proto_compile.py
proto_compile/utils.py
proto_compile/versions.py
proto_compile-0.1.7.dist-info/AUTHORS.rst
proto_compile-0.1.7.dist-info/LICENSE
proto_compile-0.1.7.dist-info/METADATA
proto_compile-0.1.7.dist-info/WHEEL
proto_compile-0.1.7.dist-info/entry_points.txt
proto_compile-0.1.7.dist-info/top_level.txt
proto_compile-0.1.7.dist-info/RECORD
